{
  "clubName": "Bryne FK",
  "players": {
    "73922": {
      "name": "Jesper Gregersen",
      "cardName": "Gregersen",
      "originalVersionId": "0",
      "clubId": 1523,
      "leagueId": 41,
      "countryId": 36,
      "versionId": "2000",
      "rating": 59,
      "preferredFoot": "Right",
      "weakFoot": 3,
      "skillMoves": 2,
      "preferredPosition": "CM",
      "possiblePositions": [
        "CM"
      ],
      "playStyles": [],
      "playStylesPlus": [],
      "rolesPlus": [
        18
      ],
      "rolesPlusPlus": [
        18
      ],
      "attributes": [
        60,
        54,
        53,
        60,
        53,
        56
      ],
      "hasDynamicImage": false,
      "price": 200,
      "resourceId": 73922,
      "assetId": 73922
    },
    "76635": {
      "name": "Igor Spiridonov",
      "cardName": "Spiridonov",
      "originalVersionId": "0",
      "clubId": 1523,
      "leagueId": 41,
      "countryId": 30,
      "versionId": "2000",
      "rating": 62,
      "preferredFoot": "Right",
      "weakFoot": 3,
      "skillMoves": 1,
      "preferredPosition": "GK",
      "possiblePositions": [
        "GK"
      ],
      "playStyles": [],
      "playStylesPlus": [],
      "rolesPlus": [
        1
      ],
      "rolesPlusPlus": [
        1
      ],
      "attributes": [
        59,
        62,
        60,
        60,
        26,
        62
      ],
      "hasDynamicImage": false,
      "price": 200,
      "resourceId": 76635,
      "assetId": 76635
    },
    "76638": {
      "name": "Eirik Saunes",
      "cardName": "Saunes",
      "originalVersionId": "0",
      "clubId": 1523,
      "leagueId": 41,
      "countryId": 36,
      "versionId": "2001",
      "rating": 65,
      "preferredFoot": "Left",
      "weakFoot": 3,
      "skillMoves": 2,
      "preferredPosition": "LB",
      "possiblePositions": [
        "LB",
        "LM",
        "RM"
      ],
      "playStyles": [],
      "playStylesPlus": [],
      "rolesPlus": [
        9,
        25
      ],
      "rolesPlusPlus": [
        9,
        25
      ],
      "attributes": [
        69,
        29,
        54,
        59,
        62,
        67
      ],
      "hasDynamicImage": false,
      "price": 350,
      "resourceId": 76638,
      "assetId": 76638
    },
    "76639": {
      "name": "Lasse Qvigstad",
      "cardName": "Qvigstad",
      "originalVersionId": "0",
      "clubId": 1523,
      "leagueId": 41,
      "countryId": 36,
      "versionId": "2000",
      "rating": 61,
      "preferredFoot": "Right",
      "weakFoot": 3,
      "skillMoves": 2,
      "preferredPosition": "RB",
      "possiblePositions": [
        "LB",
        "RB",
        "RM"
      ],
      "playStyles": [],
      "playStylesPlus": [],
      "rolesPlus": [
        5,
        9
      ],
      "rolesPlusPlus": [
        5,
        9
      ],
      "attributes": [
        58,
        27,
        49,
        57,
        57,
        67
      ],
      "hasDynamicImage": false,
      "price": 200,
      "resourceId": 76639,
      "assetId": 76639
    },
    "76640": {
      "name": "Axel Kryger",
      "cardName": "Kryger",
      "originalVersionId": "0",
      "clubId": 1523,
      "leagueId": 41,
      "countryId": 36,
      "versionId": "2001",
      "rating": 65,
      "preferredFoot": "Right",
      "weakFoot": 3,
      "skillMoves": 2,
      "preferredPosition": "CDM",
      "possiblePositions": [
        "CB",
        "CDM",
        "RB"
      ],
      "playStyles": [],
      "playStylesPlus": [],
      "rolesPlus": [
        14,
        17
      ],
      "rolesPlusPlus": [
        14,
        17
      ],
      "attributes": [
        63,
        39,
        57,
        58,
        62,
        67
      ],
      "hasDynamicImage": false,
      "price": 0,
      "resourceId": 76640,
      "assetId": 76640
    },
    "76643": {
      "name": "Mats Thornes",
      "cardName": "Thornes",
      "originalVersionId": "0",
      "clubId": 1523,
      "leagueId": 41,
      "countryId": 36,
      "versionId": "2000",
      "rating": 60,
      "preferredFoot": "Right",
      "weakFoot": 3,
      "skillMoves": 2,
      "preferredPosition": "CM",
      "possiblePositions": [
        "CM",
        "LM"
      ],
      "playStyles": [],
      "playStylesPlus": [],
      "rolesPlus": [
        18
      ],
      "rolesPlusPlus": [
        18
      ],
      "attributes": [
        62,
        52,
        56,
        59,
        48,
        59
      ],
      "hasDynamicImage": false,
      "price": 200,
      "resourceId": 76643,
      "assetId": 76643
    },
    "76645": {
      "name": "Sanel Bojadžić",
      "cardName": "Bojadžić",
      "originalVersionId": "0",
      "clubId": 1523,
      "leagueId": 41,
      "countryId": 21,
      "versionId": "2000",
      "rating": 64,
      "preferredFoot": "Right",
      "weakFoot": 3,
      "skillMoves": 2,
      "preferredPosition": "ST",
      "possiblePositions": [
        "CAM",
        "ST"
      ],
      "playStyles": [],
      "playStylesPlus": [],
      "rolesPlus": [
        43,
        44
      ],
      "rolesPlusPlus": [
        43,
        44
      ],
      "attributes": [
        68,
        63,
        49,
        62,
        22,
        62
      ],
      "hasDynamicImage": false,
      "price": 200,
      "resourceId": 76645,
      "assetId": 76645
    },
    "76646": {
      "name": "Duarte Moreira",
      "cardName": "Duarte Moreira",
      "originalVersionId": "0",
      "clubId": 1523,
      "leagueId": 41,
      "countryId": 38,
      "versionId": "2001",
      "rating": 66,
      "preferredFoot": "Right",
      "weakFoot": 3,
      "skillMoves": 2,
      "preferredPosition": "ST",
      "possiblePositions": [
        "ST"
      ],
      "playStyles": [],
      "playStylesPlus": [],
      "rolesPlus": [
        42
      ],
      "rolesPlusPlus": [
        42
      ],
      "attributes": [
        72,
        65,
        52,
        64,
        19,
        64
      ],
      "hasDynamicImage": false,
      "price": 700,
      "resourceId": 76646,
      "assetId": 76646
    },
    "76647": {
      "name": "Sjur Jonassen",
      "cardName": "Jonassen",
      "originalVersionId": "0",
      "clubId": 1523,
      "leagueId": 41,
      "countryId": 36,
      "versionId": "2000",
      "rating": 61,
      "preferredFoot": "Right",
      "weakFoot": 3,
      "skillMoves": 2,
      "preferredPosition": "ST",
      "possiblePositions": [
        "ST"
      ],
      "playStyles": [],
      "playStylesPlus": [],
      "rolesPlus": [
        41
      ],
      "rolesPlusPlus": [
        41
      ],
      "attributes": [
        72,
        59,
        48,
        59,
        17,
        60
      ],
      "hasDynamicImage": false,
      "price": 200,
      "resourceId": 76647,
      "assetId": 76647
    },
    "78032": {
      "name": "Martin Åmot Lye",
      "cardName": "Lye",
      "originalVersionId": "0",
      "clubId": 1523,
      "leagueId": 41,
      "countryId": 36,
      "versionId": "2000",
      "rating": 55,
      "preferredFoot": "Right",
      "weakFoot": 3,
      "skillMoves": 2,
      "preferredPosition": "CM",
      "possiblePositions": [
        "CM"
      ],
      "playStyles": [],
      "playStylesPlus": [],
      "rolesPlus": [
        18
      ],
      "rolesPlusPlus": [
        18
      ],
      "attributes": [
        67,
        47,
        50,
        53,
        47,
        56
      ],
      "hasDynamicImage": false,
      "price": 200,
      "resourceId": 78032,
      "assetId": 78032
    },
    "186507": {
      "name": "Christian Landu-Landu",
      "cardName": "Landu-Landu",
      "originalVersionId": "0",
      "clubId": 1523,
      "leagueId": 41,
      "countryId": 36,
      "versionId": "2000",
      "rating": 63,
      "preferredFoot": "Right",
      "weakFoot": 3,
      "skillMoves": 2,
      "preferredPosition": "CDM",
      "possiblePositions": [
        "CDM",
        "CM"
      ],
      "playStyles": [],
      "playStylesPlus": [],
      "rolesPlus": [
        14
      ],
      "rolesPlusPlus": [
        14
      ],
      "attributes": [
        57,
        49,
        57,
        62,
        62,
        70
      ],
      "hasDynamicImage": false,
      "price": 200,
      "resourceId": 186507,
      "assetId": 186507
    },
    "206584": {
      "name": "Jon-Helge Tveita",
      "cardName": "Tveita",
      "originalVersionId": "1",
      "clubId": 1523,
      "leagueId": 41,
      "countryId": 36,
      "versionId": "3000",
      "rating": 61,
      "preferredFoot": "Right",
      "weakFoot": 3,
      "skillMoves": 3,
      "preferredPosition": "LM",
      "possiblePositions": [
        "LM",
        "LW",
        "RM"
      ],
      "playStyles": [],
      "playStylesPlus": [],
      "rolesPlus": [
        27
      ],
      "rolesPlusPlus": [
        27
      ],
      "attributes": [
        64,
        56,
        57,
        59,
        60,
        69
      ],
      "hasDynamicImage": false,
      "price": 200,
      "resourceId": 206584,
      "assetId": 206584
    },
    "231509": {
      "name": "Anton Cajtoft",
      "cardName": "Cajtoft",
      "originalVersionId": "0",
      "clubId": 1523,
      "leagueId": 41,
      "countryId": 46,
      "versionId": "2000",
      "rating": 64,
      "preferredFoot": "Right",
      "weakFoot": 3,
      "skillMoves": 1,
      "preferredPosition": "GK",
      "possiblePositions": [
        "GK"
      ],
      "playStyles": [],
      "playStylesPlus": [],
      "rolesPlus": [
        1
      ],
      "rolesPlusPlus": [
        1
      ],
      "attributes": [
        63,
        62,
        65,
        63,
        29,
        64
      ],
      "hasDynamicImage": false,
      "price": 200,
      "resourceId": 231509,
      "assetId": 231509
    },
    "239955": {
      "name": "Jens Berland Husebø",
      "cardName": "Husebø",
      "originalVersionId": "1",
      "clubId": 1523,
      "leagueId": 41,
      "countryId": 36,
      "versionId": "3000",
      "rating": 64,
      "preferredFoot": "Right",
      "weakFoot": 3,
      "skillMoves": 2,
      "preferredPosition": "CB",
      "possiblePositions": [
        "CB"
      ],
      "playStyles": [],
      "playStylesPlus": [],
      "rolesPlus": [
        11,
        12
      ],
      "rolesPlusPlus": [
        11,
        12
      ],
      "attributes": [
        61,
        32,
        43,
        54,
        63,
        68
      ],
      "hasDynamicImage": false,
      "price": 0,
      "resourceId": 239955,
      "assetId": 239955
    },
    "242600": {
      "name": "Nicklas Strunck",
      "cardName": "Strunck",
      "originalVersionId": "1",
      "clubId": 1523,
      "leagueId": 41,
      "countryId": 13,
      "versionId": "3000",
      "rating": 62,
      "preferredFoot": "Right",
      "weakFoot": 4,
      "skillMoves": 3,
      "preferredPosition": "CM",
      "possiblePositions": [
        "CM"
      ],
      "playStyles": [],
      "playStylesPlus": [],
      "rolesPlus": [
        18
      ],
      "rolesPlusPlus": [
        18
      ],
      "attributes": [
        66,
        54,
        57,
        64,
        56,
        65
      ],
      "hasDynamicImage": false,
      "price": 200,
      "resourceId": 242600,
      "assetId": 242600
    },
    "247107": {
      "name": "Alfred Scriven",
      "cardName": "Scriven",
      "originalVersionId": "0",
      "clubId": 1523,
      "leagueId": 41,
      "countryId": 36,
      "versionId": "2000",
      "rating": 64,
      "preferredFoot": "Right",
      "weakFoot": 2,
      "skillMoves": 3,
      "preferredPosition": "LM",
      "possiblePositions": [
        "LM",
        "LW",
        "RM",
        "ST"
      ],
      "playStyles": [],
      "playStylesPlus": [],
      "rolesPlus": [
        23,
        30
      ],
      "rolesPlusPlus": [
        23,
        30
      ],
      "attributes": [
        68,
        62,
        60,
        62,
        20,
        65
      ],
      "hasDynamicImage": false,
      "price": 200,
      "resourceId": 247107,
      "assetId": 247107
    },
    "247490": {
      "name": "Jacob Haahr",
      "cardName": "Haahr",
      "originalVersionId": "1",
      "clubId": 1523,
      "leagueId": 41,
      "countryId": 13,
      "versionId": "3000",
      "rating": 63,
      "preferredFoot": "Right",
      "weakFoot": 2,
      "skillMoves": 2,
      "preferredPosition": "CB",
      "possiblePositions": [
        "CB"
      ],
      "playStyles": [],
      "playStylesPlus": [],
      "rolesPlus": [
        11,
        13
      ],
      "rolesPlusPlus": [
        11,
        13
      ],
      "attributes": [
        66,
        25,
        42,
        56,
        62,
        59
      ],
      "hasDynamicImage": false,
      "price": 200,
      "resourceId": 247490,
      "assetId": 247490
    },
    "253110": {
      "name": "Jan de Boer",
      "cardName": "de Boer",
      "originalVersionId": "0",
      "clubId": 1523,
      "leagueId": 41,
      "countryId": 34,
      "versionId": "2000",
      "rating": 64,
      "preferredFoot": "Right",
      "weakFoot": 2,
      "skillMoves": 1,
      "preferredPosition": "GK",
      "possiblePositions": [
        "GK"
      ],
      "playStyles": [],
      "playStylesPlus": [],
      "rolesPlus": [
        1
      ],
      "rolesPlusPlus": [
        1
      ],
      "attributes": [
        63,
        62,
        63,
        62,
        18,
        64
      ],
      "hasDynamicImage": false,
      "price": 200,
      "resourceId": 253110,
      "assetId": 253110
    },
    "256809": {
      "name": "Lars Erik Sødal",
      "cardName": "Sødal",
      "originalVersionId": "0",
      "clubId": 1523,
      "leagueId": 41,
      "countryId": 36,
      "versionId": "2000",
      "rating": 63,
      "preferredFoot": "Right",
      "weakFoot": 2,
      "skillMoves": 2,
      "preferredPosition": "CM",
      "possiblePositions": [
        "CM"
      ],
      "playStyles": [],
      "playStylesPlus": [],
      "rolesPlus": [
        18,
        19
      ],
      "rolesPlusPlus": [
        18,
        19
      ],
      "attributes": [
        58,
        54,
        57,
        62,
        55,
        66
      ],
      "hasDynamicImage": false,
      "price": 200,
      "resourceId": 256809,
      "assetId": 256809
    },
    "279735": {
      "name": "Remi-André Svindland",
      "cardName": "Svindland",
      "originalVersionId": "1",
      "clubId": 1523,
      "leagueId": 41,
      "countryId": 36,
      "versionId": "3000",
      "rating": 64,
      "preferredFoot": "Right",
      "weakFoot": 3,
      "skillMoves": 3,
      "preferredPosition": "RW",
      "possiblePositions": [
        "CM",
        "RM",
        "RW"
      ],
      "playStyles": [],
      "playStylesPlus": [],
      "rolesPlus": [
        18,
        35,
        37
      ],
      "rolesPlusPlus": [
        18,
        35,
        37
      ],
      "attributes": [
        67,
        60,
        63,
        64,
        41,
        66
      ],
      "hasDynamicImage": false,
      "price": 200,
      "resourceId": 279735,
      "assetId": 279735
    }
  }
}