{
  "72809": {
    "name": "Arkell Jude-Boyd",
    "cardName": "Jude-Boyd",
    "originalVersionId": "1",
    "clubId": 1936,
    "leagueId": 61,
    "countryId": 90,
    "versionId": "3000",
    "rating": 61,
    "preferredFoot": "Right",
    "weakFoot": 3,
    "skillMoves": 2,
    "preferredPosition": "RB",
    "possiblePositions": [
      "RB",
      "RM"
    ],
    "playStyles": [],
    "playStylesPlus": [],
    "rolesPlus": [
      3,
      5
    ],
    "rolesPlusPlus": [
      3,
      5
    ],
    "attributes": [
      75,
      52,
      52,
      58,
      56,
      69
    ],
    "hasDynamicImage": false,
    "price": 200,
    "resourceId": 72809,
    "assetId": 72809
  },
  "237204": {
    "name": "Reeco Hackett",
    "cardName": "Hackett",
    "originalVersionId": "1",
    "clubId": 149,
    "leagueId": 60,
    "countryId": 90,
    "versionId": "3001",
    "rating": 66,
    "preferredFoot": "Left",
    "weakFoot": 3,
    "skillMoves": 3,
    "preferredPosition": "LM",
    "possiblePositions": [
      "CAM",
      "LB",
      "LM"
    ],
    "playStyles": [
      21
    ],
    "playStylesPlus": [],
    "rolesPlus": [
      10,
      27,
      28,
      33
    ],
    "rolesPlusPlus": [
      10,
      27,
      28,
      33
    ],
    "attributes": [
      80,
      63,
      60,
      65,
      50,
      66
    ],
    "hasDynamicImage": false,
    "price": 400,
    "resourceId": 237204,
    "assetId": 237204
  },
  "244240": {
    "name": "Chris Forino",
    "cardName": "Forino",
    "originalVersionId": "0",
    "clubId": 4,
    "leagueId": 60,
    "countryId": 90,
    "versionId": "2001",
    "rating": 66,
    "preferredFoot": "Right",
    "weakFoot": 4,
    "skillMoves": 2,
    "preferredPosition": "CB",
    "possiblePositions": [
      "CB"
    ],
    "playStyles": [],
    "playStylesPlus": [],
    "rolesPlus": [
      12,
      48
    ],
    "rolesPlusPlus": [
      12,
      48
    ],
    "attributes": [
      70,
      24,
      39,
      47,
      65,
      76
    ],
    "hasDynamicImage": false,
    "price": 500,
    "resourceId": 244240,
    "assetId": 244240
  }
}