{
  "210047": {
    "clubId": 13,
    "leagueId": 13,
    "countryId": 47,
    "versionId": "2002",
    "rating": 82,
    "preferredFoot": "Right",
    "weakFoot": 3,
    "skillMoves": 2,
    "preferredPosition": "CB",
    "possiblePositions": [
      "CB"
    ],
    "playStyles": [
      10,
      16,
      2,
      4
    ],
    "playStylesPlus": [],
    "rolesPlus": [
      11,
      12,
      13
    ],
    "rolesPlusPlus": [
      11,
      12,
      13
    ],
    "attributes": [
      51,
      68,
      76,
      73,
      84,
      80
    ],
    "hasDynamicImage": false,
    "price": 700,
    "resourceId": 210047,
    "assetId": 210047,
    "originalVersionId": 0
  },
  "cardName": "Schär",
  "name": "Fabian Schär"
}