{
  "212366": {
    "clubId": 4,
    "leagueId": 60,
    "countryId": 50,
    "versionId": "3001",
    "rating": 68,
    "preferredFoot": "Right",
    "weakFoot": 4,
    "skillMoves": 3,
    "preferredPosition": "CDM",
    "possiblePositions": [
      "CB",
      "CDM",
      "CM"
    ],
    "playStyles": [
      10,
      24
    ],
    "playStylesPlus": [],
    "rolesPlus": [
      15,
      16,
      18
    ],
    "rolesPlusPlus": [
      15,
      16,
      18
    ],
    "attributes": [
      79,
      57,
      69,
      71,
      62,
      64
    ],
    "hasDynamicImage": false,
    "price": 750,
    "resourceId": 212366,
    "assetId": 212366,
    "originalVersionId": 1
  },
  "cardName": "Sheehan",
  "name": "Josh Sheehan"
}