{
  "212934": {
    "clubId": 113888,
    "leagueId": 2244,
    "countryId": 18,
    "versionId": "2001",
    "rating": 71,
    "preferredFoot": "Right",
    "weakFoot": 4,
    "skillMoves": 3,
    "preferredPosition": "LW",
    "possiblePositions": [
      "CAM",
      "LM",
      "LW"
    ],
    "playStyles": [
      20
    ],
    "playStylesPlus": [],
    "rolesPlus": [
      38
    ],
    "rolesPlusPlus": [
      38
    ],
    "attributes": [
      74,
      68,
      69,
      73,
      33,
      60
    ],
    "hasDynamicImage": false,
    "price": 750,
    "resourceId": 212934,
    "assetId": 212934,
    "originalVersionId": 0
  },
  "cardName": "Zoubir",
  "name": "Abdellah Zoubir"
}