{
  "229045": {
    "clubId": 111276,
    "leagueId": 17,
    "countryId": 116,
    "versionId": "3001",
    "rating": 65,
    "preferredFoot": "Right",
    "weakFoot": 3,
    "skillMoves": 3,
    "preferredPosition": "ST",
    "possiblePositions": [
      "ST"
    ],
    "playStyles": [
      0,
      25
    ],
    "playStylesPlus": [],
    "rolesPlus": [
      41
    ],
    "rolesPlusPlus": [
      41
    ],
    "attributes": [
      85,
      64,
      56,
      63,
      23,
      74
    ],
    "hasDynamicImage": false,
    "price": 500,
    "resourceId": 229045,
    "assetId": 229045,
    "originalVersionId": 1
  },
  "cardName": "Kanté",
  "name": "Aboubakary Kanté"
}