{
  "231461": {
    "clubId": 114168,
    "leagueId": 2149,
    "countryId": 159,
    "versionId": "2000",
    "rating": 56,
    "preferredFoot": "Right",
    "weakFoot": 3,
    "skillMoves": 2,
    "preferredPosition": "CM",
    "possiblePositions": [
      "CB",
      "CDM",
      "CM"
    ],
    "playStyles": [
      27
    ],
    "playStylesPlus": [],
    "rolesPlus": [
      14,
      19,
      20
    ],
    "rolesPlusPlus": [
      14,
      19,
      20
    ],
    "attributes": [
      33,
      55,
      51,
      58,
      55,
      72
    ],
    "hasDynamicImage": false,
    "price": 200,
    "resourceId": 231461,
    "assetId": 231461,
    "originalVersionId": 0
  },
  "cardName": "Halder",
  "name": "Pronay Halder"
}