{
  "232066": {
    "clubId": 111006,
    "leagueId": 1014,
    "countryId": 58,
    "versionId": "2001",
    "rating": 68,
    "preferredFoot": "Right",
    "weakFoot": 3,
    "skillMoves": 3,
    "preferredPosition": "ST",
    "possiblePositions": [
      "ST"
    ],
    "playStyles": [],
    "playStylesPlus": [],
    "rolesPlus": [
      42,
      44
    ],
    "rolesPlusPlus": [
      42,
      44
    ],
    "attributes": [
      59,
      68,
      51,
      66,
      30,
      67
    ],
    "hasDynamicImage": false,
    "price": 550,
    "resourceId": 232066,
    "assetId": 232066,
    "originalVersionId": 0
  },
  "cardName": "González",
  "name": "Walter González"
}