{
  "234339": {
    "clubId": 2056,
    "leagueId": 83,
    "countryId": 167,
    "versionId": "3000",
    "rating": 59,
    "preferredFoot": "Right",
    "weakFoot": 3,
    "skillMoves": 2,
    "preferredPosition": "ST",
    "possiblePositions": [
      "LM",
      "RW",
      "ST"
    ],
    "playStyles": [],
    "playStylesPlus": [],
    "rolesPlus": [
      41
    ],
    "rolesPlusPlus": [
      41
    ],
    "attributes": [
      70,
      56,
      46,
      59,
      34,
      59
    ],
    "hasDynamicImage": false,
    "price": 200,
    "resourceId": 234339,
    "assetId": 234339,
    "originalVersionId": 1
  },
  "cardName": "Park Dae Hoon",
  "name": "Park Dae Hoon"
}