{
  "234925": {
    "clubId": 1971,
    "leagueId": 10,
    "countryId": 34,
    "versionId": "2001",
    "rating": 65,
    "preferredFoot": "Left",
    "weakFoot": 3,
    "skillMoves": 2,
    "preferredPosition": "CB",
    "possiblePositions": [
      "CB"
    ],
    "playStyles": [],
    "playStylesPlus": [],
    "rolesPlus": [
      13
    ],
    "rolesPlusPlus": [
      13
    ],
    "attributes": [
      56,
      45,
      66,
      64,
      66,
      62
    ],
    "hasDynamicImage": false,
    "price": 0,
    "resourceId": 234925,
    "assetId": 234925,
    "originalVersionId": 0
  },
  "cardName": "Pierie",
  "name": "Kik Pierie"
}