{
  "237490": {
    "clubId": 523,
    "leagueId": 2076,
    "countryId": 21,
    "versionId": "2001",
    "rating": 67,
    "preferredFoot": "Right",
    "weakFoot": 3,
    "skillMoves": 3,
    "preferredPosition": "CDM",
    "possiblePositions": [
      "CB",
      "CDM",
      "CM"
    ],
    "playStyles": [
      14,
      16,
      24,
      26,
      8
    ],
    "playStylesPlus": [],
    "rolesPlus": [
      15,
      21
    ],
    "rolesPlusPlus": [
      15,
      21
    ],
    "attributes": [
      68,
      51,
      61,
      68,
      61,
      70
    ],
    "hasDynamicImage": false,
    "price": 400,
    "resourceId": 237490,
    "assetId": 237490,
    "originalVersionId": 0
  },
  "cardName": "Sontheimer",
  "name": "Patrick Sontheimer"
}