{
  "237640": {
    "clubId": 86,
    "leagueId": 50,
    "countryId": 1,
    "versionId": "3001",
    "rating": 73,
    "preferredFoot": "Right",
    "weakFoot": 4,
    "skillMoves": 3,
    "preferredPosition": "CAM",
    "possiblePositions": [
      "CAM",
      "CM",
      "LM",
      "RW"
    ],
    "playStyles": [
      20
    ],
    "playStylesPlus": [],
    "rolesPlus": [
      30,
      33,
      36
    ],
    "rolesPlusPlus": [
      30,
      33,
      36
    ],
    "attributes": [
      75,
      67,
      72,
      77,
      58,
      65
    ],
    "hasDynamicImage": false,
    "price": 2700,
    "resourceId": 237640,
    "assetId": 237640,
    "originalVersionId": 1
  },
  "cardName": "Bajrami",
  "name": "Nedim Bajrami"
}