{
  "239179": {
    "clubId": 114326,
    "leagueId": 66,
    "countryId": 10,
    "versionId": "3001",
    "rating": 70,
    "preferredFoot": "Right",
    "weakFoot": 3,
    "skillMoves": 2,
    "preferredPosition": "CB",
    "possiblePositions": [
      "CB"
    ],
    "playStyles": [
      10,
      15,
      17
    ],
    "playStylesPlus": [],
    "rolesPlus": [
      12,
      48
    ],
    "rolesPlusPlus": [
      12,
      48
    ],
    "attributes": [
      69,
      40,
      57,
      60,
      68,
      81
    ],
    "hasDynamicImage": false,
    "price": 550,
    "resourceId": 239179,
    "assetId": 239179,
    "originalVersionId": 1
  },
  "cardName": "Arsenić",
  "name": "Zoran Arsenić"
}