{
  "242423": {
    "clubId": 1917,
    "leagueId": 60,
    "countryId": 14,
    "versionId": "2001",
    "rating": 65,
    "preferredFoot": "Right",
    "weakFoot": 3,
    "skillMoves": 3,
    "preferredPosition": "CAM",
    "possiblePositions": [
      "CAM",
      "CM",
      "RM"
    ],
    "playStyles": [],
    "playStylesPlus": [],
    "rolesPlus": [
      22,
      23,
      31,
      33
    ],
    "rolesPlusPlus": [
      22,
      23,
      31,
      33
    ],
    "attributes": [
      67,
      61,
      63,
      67,
      55,
      62
    ],
    "hasDynamicImage": false,
    "price": 700,
    "resourceId": 242423,
    "assetId": 242423,
    "originalVersionId": 0
  },
  "cardName": "Wright",
  "name": "Callum Wright"
}