{
  "251431": {
    "clubId": 256,
    "leagueId": 80,
    "countryId": 21,
    "versionId": "2001",
    "rating": 70,
    "preferredFoot": "Left",
    "weakFoot": 3,
    "skillMoves": 3,
    "preferredPosition": "ST",
    "possiblePositions": [
      "CAM",
      "LM",
      "ST"
    ],
    "playStyles": [
      29
    ],
    "playStylesPlus": [],
    "rolesPlus": [
      30,
      42,
      43
    ],
    "rolesPlusPlus": [
      30,
      42,
      43
    ],
    "attributes": [
      77,
      70,
      63,
      69,
      31,
      75
    ],
    "hasDynamicImage": false,
    "price": 0,
    "resourceId": 251431,
    "assetId": 251431,
    "originalVersionId": 0
  },
  "50583079": {
    "clubId": 209,
    "leagueId": 80,
    "countryId": 21,
    "versionId": "2001",
    "rating": 70,
    "preferredFoot": "Left",
    "weakFoot": 3,
    "skillMoves": 3,
    "preferredPosition": "ST",
    "possiblePositions": [
      "CAM",
      "LM",
      "ST"
    ],
    "playStyles": [
      29
    ],
    "playStylesPlus": [],
    "rolesPlus": [
      30,
      42,
      43
    ],
    "rolesPlusPlus": [
      30,
      42,
      43
    ],
    "attributes": [
      77,
      70,
      63,
      69,
      31,
      75
    ],
    "hasDynamicImage": false,
    "price": 450,
    "resourceId": 50583079,
    "assetId": 251431,
    "originalVersionId": 0
  },
  "cardName": "Malone",
  "name": "Maurice Malone"
}