{
  "251773": {
    "clubId": 114611,
    "leagueId": 1014,
    "countryId": 61,
    "versionId": "2001",
    "rating": 68,
    "preferredFoot": "Right",
    "weakFoot": 2,
    "skillMoves": 1,
    "preferredPosition": "GK",
    "possiblePositions": [
      "GK"
    ],
    "playStyles": [
      35
    ],
    "playStylesPlus": [],
    "rolesPlus": [
      1
    ],
    "rolesPlusPlus": [
      1
    ],
    "attributes": [
      67,
      65,
      65,
      69,
      24,
      72
    ],
    "hasDynamicImage": false,
    "price": 400,
    "resourceId": 251773,
    "assetId": 251773,
    "originalVersionId": 0
  },
  "cardName": "Romero",
  "name": "Luis Romero"
}