{
  "251857": {
    "clubId": 583,
    "leagueId": 2076,
    "countryId": 21,
    "versionId": "3000",
    "rating": 59,
    "preferredFoot": "Right",
    "weakFoot": 2,
    "skillMoves": 2,
    "preferredPosition": "CB",
    "possiblePositions": [
      "CB"
    ],
    "playStyles": [],
    "playStylesPlus": [],
    "rolesPlus": [
      11
    ],
    "rolesPlusPlus": [
      11
    ],
    "attributes": [
      59,
      23,
      29,
      41,
      57,
      72
    ],
    "hasDynamicImage": false,
    "price": 200,
    "resourceId": 251857,
    "assetId": 251857,
    "originalVersionId": 1
  },
  "cardName": "Frisorger",
  "name": "Kevin Frisorger"
}