{
  "252205": {
    "clubId": 131447,
    "leagueId": 17,
    "countryId": 18,
    "versionId": "2000",
    "rating": 60,
    "preferredFoot": "Right",
    "weakFoot": 3,
    "skillMoves": 2,
    "preferredPosition": "ST",
    "possiblePositions": [
      "ST"
    ],
    "playStyles": [],
    "playStylesPlus": [],
    "rolesPlus": [
      41
    ],
    "rolesPlusPlus": [
      41
    ],
    "attributes": [
      56,
      60,
      42,
      53,
      29,
      73
    ],
    "hasDynamicImage": false,
    "price": 200,
    "resourceId": 252205,
    "assetId": 252205,
    "originalVersionId": 0
  },
  "cardName": "Rambaud",
  "name": "Thibault Rambaud"
}