{
  "252746": {
    "clubId": 1744,
    "leagueId": 32,
    "countryId": 27,
    "versionId": "3001",
    "rating": 67,
    "preferredFoot": "Left",
    "weakFoot": 3,
    "skillMoves": 2,
    "preferredPosition": "CB",
    "possiblePositions": [
      "CB"
    ],
    "playStyles": [],
    "playStylesPlus": [],
    "rolesPlus": [
      11,
      48
    ],
    "rolesPlusPlus": [
      11,
      48
    ],
    "attributes": [
      75,
      50,
      59,
      62,
      66,
      69
    ],
    "hasDynamicImage": false,
    "price": 500,
    "resourceId": 252746,
    "assetId": 252746,
    "originalVersionId": 1
  },
  "cardName": "Cauz",
  "name": "Cristian Cauz"
}