{
  "252960": {
    "clubId": 72,
    "leagueId": 16,
    "countryId": 46,
    "versionId": "3001",
    "rating": 71,
    "preferredFoot": "Right",
    "weakFoot": 3,
    "skillMoves": 3,
    "preferredPosition": "LW",
    "possiblePositions": [
      "CAM",
      "LM",
      "LW",
      "ST"
    ],
    "playStyles": [
      20,
      25,
      27,
      6
    ],
    "playStylesPlus": [],
    "rolesPlus": [
      33,
      38,
      39,
      43
    ],
    "rolesPlusPlus": [
      33,
      38,
      39,
      43
    ],
    "attributes": [
      85,
      67,
      60,
      75,
      41,
      68
    ],
    "hasDynamicImage": false,
    "price": 500,
    "resourceId": 252960,
    "assetId": 252960,
    "originalVersionId": 1
  },
  "cardName": "Jansson",
  "name": "Isak Jansson"
}