{
  "254138": {
    "clubId": 127,
    "leagueId": 61,
    "countryId": 198,
    "versionId": "3000",
    "rating": 62,
    "preferredFoot": "Left",
    "weakFoot": 3,
    "skillMoves": 2,
    "preferredPosition": "ST",
    "possiblePositions": [
      "ST"
    ],
    "playStyles": [
      21
    ],
    "playStylesPlus": [],
    "rolesPlus": [
      44
    ],
    "rolesPlusPlus": [
      44
    ],
    "attributes": [
      72,
      60,
      49,
      56,
      24,
      72
    ],
    "hasDynamicImage": false,
    "price": 0,
    "resourceId": 254138,
    "assetId": 254138,
    "originalVersionId": 1
  },
  "cardName": "Mata",
  "name": "Max Mata"
}