{
  "254258": {
    "clubId": 718,
    "leagueId": 308,
    "countryId": 38,
    "versionId": "2001",
    "rating": 69,
    "preferredFoot": "Left",
    "weakFoot": 3,
    "skillMoves": 3,
    "preferredPosition": "LB",
    "possiblePositions": [
      "LB",
      "LM"
    ],
    "playStyles": [
      21
    ],
    "playStylesPlus": [],
    "rolesPlus": [
      9,
      27
    ],
    "rolesPlusPlus": [
      9,
      27
    ],
    "attributes": [
      77,
      51,
      58,
      68,
      66,
      70
    ],
    "hasDynamicImage": false,
    "price": 500,
    "resourceId": 254258,
    "assetId": 254258,
    "originalVersionId": 0
  },
  "cardName": "Nilton Varela",
  "name": "Nilton Varela"
}