{
  "255565": {
    "clubId": 1808,
    "leagueId": 13,
    "countryId": 163,
    "versionId": "3002",
    "rating": 82,
    "preferredFoot": "Right",
    "weakFoot": 4,
    "skillMoves": 4,
    "preferredPosition": "LM",
    "possiblePositions": [
      "LM",
      "LW"
    ],
    "playStyles": [
      0,
      20,
      22,
      25
    ],
    "playStylesPlus": [],
    "rolesPlus": [
      30
    ],
    "rolesPlusPlus": [
      30
    ],
    "attributes": [
      87,
      73,
      76,
      86,
      57,
      64
    ],
    "hasDynamicImage": false,
    "price": 750,
    "resourceId": 255565,
    "assetId": 255565,
    "originalVersionId": 1
  },
  "cardName": "Mitoma",
  "name": "Kaoru Mitoma"
}