{
  "258273": {
    "clubId": 15040,
    "leagueId": 80,
    "countryId": 4,
    "versionId": "3000",
    "rating": 63,
    "preferredFoot": "Right",
    "weakFoot": 3,
    "skillMoves": 3,
    "preferredPosition": "CM",
    "possiblePositions": [
      "CDM",
      "CM"
    ],
    "playStyles": [],
    "playStylesPlus": [],
    "rolesPlus": [
      14,
      18
    ],
    "rolesPlusPlus": [
      14,
      18
    ],
    "attributes": [
      78,
      58,
      60,
      67,
      55,
      54
    ],
    "hasDynamicImage": false,
    "price": 200,
    "resourceId": 258273,
    "assetId": 258273,
    "originalVersionId": 1
  },
  "cardName": "Naschberger",
  "name": "Johannes Naschberger"
}