{
  "261106": {
    "clubId": 980,
    "leagueId": 83,
    "countryId": 167,
    "versionId": "2000",
    "rating": 57,
    "preferredFoot": "Right",
    "weakFoot": 2,
    "skillMoves": 1,
    "preferredPosition": "GK",
    "possiblePositions": [
      "GK"
    ],
    "playStyles": [],
    "playStylesPlus": [],
    "rolesPlus": [
      1
    ],
    "rolesPlusPlus": [
      1
    ],
    "attributes": [
      59,
      54,
      54,
      58,
      29,
      55
    ],
    "hasDynamicImage": false,
    "price": 200,
    "resourceId": 261106,
    "assetId": 261106,
    "originalVersionId": 0
  },
  "cardName": "Lee Jun Seo",
  "name": "Lee Jun Seo"
}