{
  "263229": {
    "clubId": 50,
    "leagueId": 31,
    "countryId": 52,
    "versionId": "2001",
    "rating": 67,
    "preferredFoot": "Left",
    "weakFoot": 4,
    "skillMoves": 2,
    "preferredPosition": "ST",
    "possiblePositions": [
      "ST"
    ],
    "playStyles": [
      29,
      4
    ],
    "playStylesPlus": [],
    "rolesPlus": [
      41
    ],
    "rolesPlusPlus": [
      41
    ],
    "attributes": [
      55,
      67,
      49,
      62,
      30,
      71
    ],
    "hasDynamicImage": false,
    "price": 500,
    "resourceId": 263229,
    "assetId": 263229,
    "originalVersionId": 0
  },
  "cardName": "Pellegrino",
  "name": "Mateo Pellegrino"
}