{
  "267318": {
    "clubId": 116308,
    "leagueId": 2221,
    "countryId": 95,
    "versionId": "2002",
    "rating": 80,
    "preferredFoot": "Right",
    "weakFoot": 3,
    "skillMoves": 4,
    "preferredPosition": "CM",
    "possiblePositions": [
      "CAM",
      "CM"
    ],
    "playStyles": [
      20,
      3
    ],
    "playStylesPlus": [],
    "rolesPlus": [
      18,
      22,
      33
    ],
    "rolesPlusPlus": [
      18,
      22,
      33
    ],
    "attributes": [
      66,
      76,
      81,
      80,
      59,
      67
    ],
    "hasDynamicImage": false,
    "price": 600,
    "resourceId": 267318,
    "assetId": 267318,
    "originalVersionId": 0
  },
  "cardName": "DeMelo",
  "name": "Savannah DeMelo"
}