{
  "270340": {
    "clubId": 1815,
    "leagueId": 17,
    "countryId": 97,
    "versionId": "2000",
    "rating": 60,
    "preferredFoot": "Right",
    "weakFoot": 2,
    "skillMoves": 2,
    "preferredPosition": "CAM",
    "possiblePositions": [
      "CAM",
      "CM"
    ],
    "playStyles": [],
    "playStylesPlus": [],
    "rolesPlus": [
      31
    ],
    "rolesPlusPlus": [
      31
    ],
    "attributes": [
      72,
      54,
      55,
      68,
      20,
      33
    ],
    "hasDynamicImage": false,
    "price": 200,
    "resourceId": 270340,
    "assetId": 270340,
    "originalVersionId": 0
  },
  "cardName": "Bellache",
  "name": "Yuliwes Bellache"
}