{
  "270741": {
    "clubId": 113299,
    "leagueId": 2149,
    "countryId": 129,
    "versionId": "2001",
    "rating": 68,
    "preferredFoot": "Right",
    "weakFoot": 4,
    "skillMoves": 4,
    "preferredPosition": "LM",
    "possiblePositions": [
      "LM",
      "LW",
      "ST"
    ],
    "playStyles": [
      21,
      6
    ],
    "playStylesPlus": [],
    "rolesPlus": [
      30,
      40,
      43
    ],
    "rolesPlusPlus": [
      30,
      40,
      43
    ],
    "attributes": [
      82,
      65,
      62,
      68,
      31,
      65
    ],
    "hasDynamicImage": false,
    "price": 1900,
    "resourceId": 270741,
    "assetId": 270741,
    "originalVersionId": 0
  },
  "cardName": "Sadaoui",
  "name": "Noah Wail Jacob Sadaoui"
}