{
  "271406": {
    "clubId": 131386,
    "leagueId": 2215,
    "countryId": 21,
    "versionId": "2001",
    "rating": 71,
    "preferredFoot": "Right",
    "weakFoot": 5,
    "skillMoves": 3,
    "preferredPosition": "CAM",
    "possiblePositions": [
      "CAM",
      "CM"
    ],
    "playStyles": [],
    "playStylesPlus": [],
    "rolesPlus": [
      31
    ],
    "rolesPlusPlus": [
      31
    ],
    "attributes": [
      68,
      62,
      61,
      74,
      37,
      57
    ],
    "hasDynamicImage": false,
    "price": 450,
    "resourceId": 271406,
    "assetId": 271406,
    "originalVersionId": 0
  },
  "cardName": "Brengel",
  "name": "Jonna Brengel"
}