{
  "272314": {
    "clubId": 131487,
    "leagueId": 2012,
    "countryId": 155,
    "versionId": "2000",
    "rating": 58,
    "preferredFoot": "Right",
    "weakFoot": 2,
    "skillMoves": 1,
    "preferredPosition": "GK",
    "possiblePositions": [
      "GK"
    ],
    "playStyles": [],
    "playStylesPlus": [],
    "rolesPlus": [
      2
    ],
    "rolesPlusPlus": [
      2
    ],
    "attributes": [
      58,
      56,
      52,
      65,
      17,
      57
    ],
    "hasDynamicImage": false,
    "price": 200,
    "resourceId": 272314,
    "assetId": 272314,
    "originalVersionId": 0
  },
  "cardName": "Peng Peng",
  "name": "Peng Peng"
}