{
  "272930": {
    "clubId": 674,
    "leagueId": 4,
    "countryId": 103,
    "versionId": "3000",
    "rating": 63,
    "preferredFoot": "Left",
    "weakFoot": 2,
    "skillMoves": 2,
    "preferredPosition": "CB",
    "possiblePositions": [
      "CB"
    ],
    "playStyles": [
      18
    ],
    "playStylesPlus": [],
    "rolesPlus": [
      11,
      12
    ],
    "rolesPlusPlus": [
      11,
      12
    ],
    "attributes": [
      70,
      35,
      52,
      53,
      57,
      79
    ],
    "hasDynamicImage": false,
    "price": 200,
    "resourceId": 272930,
    "assetId": 272930,
    "originalVersionId": 1
  },
  "cardName": "Kotto",
  "name": "Samuel Kotto"
}