{
  "273391": {
    "clubId": 131363,
    "leagueId": 2233,
    "countryId": 42,
    "versionId": "2001",
    "rating": 68,
    "preferredFoot": "Right",
    "weakFoot": 2,
    "skillMoves": 2,
    "preferredPosition": "LB",
    "possiblePositions": [
      "CB",
      "LB",
      "LM"
    ],
    "playStyles": [],
    "playStylesPlus": [],
    "rolesPlus": [
      7
    ],
    "rolesPlusPlus": [
      7
    ],
    "attributes": [
      62,
      43,
      57,
      58,
      69,
      63
    ],
    "hasDynamicImage": false,
    "price": 450,
    "resourceId": 273391,
    "assetId": 273391,
    "originalVersionId": 0
  },
  "cardName": "Muir",
  "name": "Amy Muir"
}