{
  "276883": {
    "clubId": 132176,
    "leagueId": 2216,
    "countryId": 14,
    "versionId": "3000",
    "rating": 63,
    "preferredFoot": "Right",
    "weakFoot": 3,
    "skillMoves": 3,
    "preferredPosition": "RB",
    "possiblePositions": [
      "RB",
      "RM"
    ],
    "playStyles": [
      21
    ],
    "playStylesPlus": [],
    "rolesPlus": [
      3
    ],
    "rolesPlusPlus": [
      3
    ],
    "attributes": [
      70,
      31,
      58,
      62,
      60,
      54
    ],
    "hasDynamicImage": false,
    "price": 3500,
    "resourceId": 276883,
    "assetId": 276883,
    "originalVersionId": 1
  },
  "cardName": "Brown",
  "name": "Cerys Brown"
}