{
  "277580": {
    "clubId": 111629,
    "leagueId": 2149,
    "countryId": 159,
    "versionId": "3000",
    "rating": 54,
    "preferredFoot": "Left",
    "weakFoot": 3,
    "skillMoves": 2,
    "preferredPosition": "LB",
    "possiblePositions": [
      "CB",
      "LB",
      "LM"
    ],
    "playStyles": [],
    "playStylesPlus": [],
    "rolesPlus": [
      9,
      13
    ],
    "rolesPlusPlus": [
      9,
      13
    ],
    "attributes": [
      62,
      24,
      41,
      49,
      52,
      60
    ],
    "hasDynamicImage": false,
    "price": 200,
    "resourceId": 277580,
    "assetId": 277580,
    "originalVersionId": 1
  },
  "cardName": "Gupta",
  "name": "Jay Gupta"
}