{
  "279125": {
    "clubId": 111822,
    "leagueId": 80,
    "countryId": 4,
    "versionId": "2000",
    "rating": 57,
    "preferredFoot": "Right",
    "weakFoot": 2,
    "skillMoves": 2,
    "preferredPosition": "CB",
    "possiblePositions": [
      "CB"
    ],
    "playStyles": [],
    "playStylesPlus": [],
    "rolesPlus": [
      11
    ],
    "rolesPlusPlus": [
      11
    ],
    "attributes": [
      57,
      27,
      38,
      36,
      57,
      62
    ],
    "hasDynamicImage": false,
    "price": 200,
    "resourceId": 279125,
    "assetId": 279125,
    "originalVersionId": 0
  },
  "cardName": "Gruber",
  "name": "Tobias Gruber"
}