{
  "71864": {
    "clubId": 418,
    "leagueId": 41,
    "countryId": 36,
    "versionId": "3001",
    "rating": 66,
    "preferredFoot": "Right",
    "weakFoot": 4,
    "skillMoves": 2,
    "preferredPosition": "CB",
    "possiblePositions": [
      "CB"
    ],
    "playStyles": [
      16
    ],
    "playStylesPlus": [],
    "rolesPlus": [
      12,
      13
    ],
    "rolesPlusPlus": [
      12,
      13
    ],
    "attributes": [
      53,
      33,
      45,
      52,
      65,
      69
    ],
    "hasDynamicImage": false,
    "price": 850,
    "resourceId": 71864,
    "assetId": 71864,
    "originalVersionId": 1
  },
  "cardName": "Guddal",
  "name": "Tobias Guddal"
}