{
  "72382": {
    "clubId": 111022,
    "leagueId": 353,
    "countryId": 52,
    "versionId": "2001",
    "rating": 65,
    "preferredFoot": "Left",
    "weakFoot": 3,
    "skillMoves": 3,
    "preferredPosition": "LM",
    "possiblePositions": [
      "LB",
      "LM"
    ],
    "playStyles": [
      16
    ],
    "playStylesPlus": [],
    "rolesPlus": [
      9,
      28,
      30
    ],
    "rolesPlusPlus": [
      9,
      28,
      30
    ],
    "attributes": [
      76,
      60,
      59,
      66,
      29,
      58
    ],
    "hasDynamicImage": false,
    "price": 400,
    "resourceId": 72382,
    "assetId": 72382,
    "originalVersionId": 0
  },
  "cardName": "Velázquez",
  "name": "Juan Martín Velázquez"
}