{
  "74987": {
    "clubId": 1745,
    "leagueId": 31,
    "countryId": 43,
    "versionId": "2000",
    "rating": 64,
    "preferredFoot": "Right",
    "weakFoot": 3,
    "skillMoves": 3,
    "preferredPosition": "RM",
    "possiblePositions": [
      "RB",
      "RM",
      "RW"
    ],
    "playStyles": [],
    "playStylesPlus": [],
    "rolesPlus": [
      23
    ],
    "rolesPlusPlus": [
      23
    ],
    "attributes": [
      70,
      63,
      62,
      62,
      32,
      59
    ],
    "hasDynamicImage": false,
    "price": 0,
    "resourceId": 74987,
    "assetId": 74987,
    "originalVersionId": 0
  },
  "cardName": "Kováčik",
  "name": "Peter Kováčik"
}