{
  "75605": {
    "clubId": 243,
    "leagueId": 53,
    "countryId": 45,
    "versionId": "2002",
    "rating": 77,
    "preferredFoot": "Right",
    "weakFoot": 3,
    "skillMoves": 2,
    "preferredPosition": "CB",
    "possiblePositions": [
      "CB",
      "RB",
      "RM"
    ],
    "playStyles": [],
    "playStylesPlus": [],
    "rolesPlus": [
      3,
      11
    ],
    "rolesPlusPlus": [
      3,
      11
    ],
    "attributes": [
      74,
      37,
      55,
      71,
      78,
      76
    ],
    "hasDynamicImage": false,
    "price": 700,
    "resourceId": 75605,
    "assetId": 75605,
    "originalVersionId": 0
  },
  "cardName": "Asencio",
  "name": "Asencio"
}