{
  "77593": {
    "clubId": 110,
    "leagueId": 13,
    "countryId": 14,
    "versionId": "2000",
    "rating": 60,
    "preferredFoot": "Right",
    "weakFoot": 3,
    "skillMoves": 3,
    "preferredPosition": "ST",
    "possiblePositions": [
      "RW",
      "ST"
    ],
    "playStyles": [],
    "playStylesPlus": [],
    "rolesPlus": [
      41
    ],
    "rolesPlusPlus": [
      41
    ],
    "attributes": [
      75,
      59,
      46,
      59,
      28,
      61
    ],
    "hasDynamicImage": false,
    "price": 950,
    "resourceId": 77593,
    "assetId": 77593,
    "originalVersionId": 0
  },
  "cardName": "Mateus Mané",
  "name": "Mateus Mané"
}