{
  "77718": {
    "clubId": 1913,
    "leagueId": 10,
    "countryId": 34,
    "versionId": "2000",
    "rating": 56,
    "preferredFoot": "Right",
    "weakFoot": 3,
    "skillMoves": 2,
    "preferredPosition": "CM",
    "possiblePositions": [
      "CM"
    ],
    "playStyles": [],
    "playStylesPlus": [],
    "rolesPlus": [
      18
    ],
    "rolesPlusPlus": [
      18
    ],
    "attributes": [
      66,
      52,
      56,
      61,
      41,
      51
    ],
    "hasDynamicImage": false,
    "price": 200,
    "resourceId": 77718,
    "assetId": 77718,
    "originalVersionId": 0
  },
  "cardName": "Jansen",
  "name": "Kai Jansen"
}