{
  "79058": {
    "clubId": 114545,
    "leagueId": 330,
    "countryId": 34,
    "versionId": "2000",
    "rating": 63,
    "preferredFoot": "Right",
    "weakFoot": 3,
    "skillMoves": 3,
    "preferredPosition": "RM",
    "possiblePositions": [
      "CAM",
      "LM",
      "RB",
      "RM"
    ],
    "playStyles": [],
    "playStylesPlus": [],
    "rolesPlus": [
      23,
      24,
      27
    ],
    "rolesPlusPlus": [
      23,
      24,
      27
    ],
    "attributes": [
      68,
      51,
      60,
      63,
      50,
      53
    ],
    "hasDynamicImage": false,
    "price": 200,
    "resourceId": 79058,
    "assetId": 79058,
    "originalVersionId": 0
  },
  "cardName": "Zakir",
  "name": "Yassine Zakir"
}