{
  "79326": {
    "clubId": 543,
    "leagueId": 2076,
    "countryId": 21,
    "versionId": "2000",
    "rating": 61,
    "preferredFoot": "Right",
    "weakFoot": 3,
    "skillMoves": 2,
    "preferredPosition": "ST",
    "possiblePositions": [
      "CAM",
      "ST"
    ],
    "playStyles": [],
    "playStylesPlus": [],
    "rolesPlus": [
      41
    ],
    "rolesPlusPlus": [
      41
    ],
    "attributes": [
      66,
      61,
      54,
      60,
      29,
      61
    ],
    "hasDynamicImage": false,
    "price": 200,
    "resourceId": 79326,
    "assetId": 79326,
    "originalVersionId": 0
  },
  "cardName": "Hermes",
  "name": "Lucas Hermes"
}