{
  "79446": {
    "clubId": 115998,
    "leagueId": 2215,
    "countryId": 195,
    "versionId": "3001",
    "rating": 74,
    "preferredFoot": "Left",
    "weakFoot": 3,
    "skillMoves": 3,
    "preferredPosition": "LW",
    "possiblePositions": [
      "LM",
      "LW"
    ],
    "playStyles": [],
    "playStylesPlus": [],
    "rolesPlus": [
      38
    ],
    "rolesPlusPlus": [
      38
    ],
    "attributes": [
      83,
      68,
      70,
      76,
      35,
      59
    ],
    "hasDynamicImage": false,
    "price": 1300,
    "resourceId": 79446,
    "assetId": 79446,
    "originalVersionId": 1
  },
  "cardName": "Freier",
  "name": "Sharn Freier"
}