{
  "79772": {
    "clubId": 15040,
    "leagueId": 80,
    "countryId": 10,
    "versionId": "2000",
    "rating": 63,
    "preferredFoot": "Right",
    "weakFoot": 2,
    "skillMoves": 2,
    "preferredPosition": "CB",
    "possiblePositions": [
      "CB"
    ],
    "playStyles": [],
    "playStylesPlus": [],
    "rolesPlus": [
      11
    ],
    "rolesPlusPlus": [
      11
    ],
    "attributes": [
      60,
      46,
      50,
      51,
      62,
      69
    ],
    "hasDynamicImage": false,
    "price": 200,
    "resourceId": 79772,
    "assetId": 79772,
    "originalVersionId": 0
  },
  "cardName": "Boras",
  "name": "Marco Boras"
}