{
  "clubName": "Parma",
  "players": {
    "192840": {
      "name": "Milan Đurić",
      "cardName": "Đurić",
      "originalVersionId": "1",
      "clubId": 50,
      "leagueId": 31,
      "countryId": 8,
      "versionId": "3001",
      "rating": 71,
      "preferredFoot": "Right",
      "weakFoot": 4,
      "skillMoves": 2,
      "preferredPosition": "ST",
      "possiblePositions": [
        "ST"
      ],
      "playStyles": [
        19,
        24,
        29,
        4
      ],
      "playStylesPlus": [],
      "rolesPlus": [
        41,
        42
      ],
      "rolesPlusPlus": [
        41,
        42
      ],
      "attributes": [
        33,
        71,
        55,
        61,
        32,
        82
      ],
      "hasDynamicImage": false,
      "price": 600,
      "resourceId": 192840,
      "assetId": 192840
    },
    "225475": {
      "name": "Hernani",
      "cardName": "Hernani",
      "originalVersionId": "0",
      "clubId": 50,
      "leagueId": 31,
      "countryId": 54,
      "versionId": "2002",
      "rating": 75,
      "preferredFoot": "Right",
      "weakFoot": 4,
      "skillMoves": 3,
      "preferredPosition": "CDM",
      "possiblePositions": [
        "CAM",
        "CDM",
        "CM"
      ],
      "playStyles": [
        2
      ],
      "playStylesPlus": [],
      "rolesPlus": [
        14,
        17,
        21,
        31
      ],
      "rolesPlusPlus": [
        14,
        17,
        21,
        31
      ],
      "attributes": [
        58,
        70,
        71,
        72,
        73,
        72
      ],
      "hasDynamicImage": false,
      "price": 350,
      "resourceId": 225475,
      "assetId": 225475
    },
    "236706": {
      "name": "Pontus Almqvist",
      "cardName": "Almqvist",
      "originalVersionId": "0",
      "clubId": 50,
      "leagueId": 31,
      "countryId": 46,
      "versionId": "2001",
      "rating": 72,
      "preferredFoot": "Left",
      "weakFoot": 4,
      "skillMoves": 4,
      "preferredPosition": "RM",
      "possiblePositions": [
        "RM",
        "RW"
      ],
      "playStyles": [],
      "playStylesPlus": [],
      "rolesPlus": [
        23,
        25,
        36
      ],
      "rolesPlusPlus": [
        23,
        25,
        36
      ],
      "attributes": [
        84,
        67,
        62,
        75,
        38,
        49
      ],
      "hasDynamicImage": false,
      "price": 550,
      "resourceId": 236706,
      "assetId": 236706
    },
    "240992": {
      "name": "Nahuel Estévez",
      "cardName": "Estévez",
      "originalVersionId": "1",
      "clubId": 50,
      "leagueId": 31,
      "countryId": 52,
      "versionId": "3001",
      "rating": 71,
      "preferredFoot": "Right",
      "weakFoot": 3,
      "skillMoves": 3,
      "preferredPosition": "CDM",
      "possiblePositions": [
        "CDM",
        "CM"
      ],
      "playStyles": [],
      "playStylesPlus": [],
      "rolesPlus": [
        14,
        17,
        21
      ],
      "rolesPlusPlus": [
        14,
        17,
        21
      ],
      "attributes": [
        68,
        70,
        73,
        73,
        66,
        64
      ],
      "hasDynamicImage": false,
      "price": 650,
      "resourceId": 240992,
      "assetId": 240992
    },
    "243154": {
      "name": "Adrian Benedyczak",
      "cardName": "Benedyczak",
      "originalVersionId": "1",
      "clubId": 50,
      "leagueId": 31,
      "countryId": 37,
      "versionId": "3001",
      "rating": 71,
      "preferredFoot": "Right",
      "weakFoot": 3,
      "skillMoves": 3,
      "preferredPosition": "LM",
      "possiblePositions": [
        "LM",
        "LW"
      ],
      "playStyles": [],
      "playStylesPlus": [],
      "rolesPlus": [
        27,
        30,
        39
      ],
      "rolesPlusPlus": [
        27,
        30,
        39
      ],
      "attributes": [
        84,
        70,
        65,
        68,
        32,
        70
      ],
      "hasDynamicImage": false,
      "price": 500,
      "resourceId": 243154,
      "assetId": 243154
    },
    "246164": {
      "name": "Lautaro Valenti",
      "cardName": "Valenti",
      "originalVersionId": "0",
      "clubId": 50,
      "leagueId": 31,
      "countryId": 52,
      "versionId": "2001",
      "rating": 68,
      "preferredFoot": "Left",
      "weakFoot": 4,
      "skillMoves": 2,
      "preferredPosition": "CB",
      "possiblePositions": [
        "CB"
      ],
      "playStyles": [
        18
      ],
      "playStylesPlus": [],
      "rolesPlus": [
        11
      ],
      "rolesPlusPlus": [
        11
      ],
      "attributes": [
        69,
        51,
        55,
        57,
        68,
        74
      ],
      "hasDynamicImage": false,
      "price": 450,
      "resourceId": 246164,
      "assetId": 246164
    },
    "252442": {
      "name": "Enrico Delprato",
      "cardName": "Delprato",
      "originalVersionId": "0",
      "clubId": 50,
      "leagueId": 31,
      "countryId": 27,
      "versionId": "2002",
      "rating": 75,
      "preferredFoot": "Right",
      "weakFoot": 3,
      "skillMoves": 2,
      "preferredPosition": "RB",
      "possiblePositions": [
        "CB",
        "RB",
        "RM"
      ],
      "playStyles": [
        15,
        17,
        28
      ],
      "playStylesPlus": [],
      "rolesPlus": [
        4,
        5,
        48
      ],
      "rolesPlusPlus": [
        4,
        5,
        48
      ],
      "attributes": [
        81,
        54,
        63,
        69,
        72,
        74
      ],
      "hasDynamicImage": false,
      "price": 450,
      "resourceId": 252442,
      "assetId": 252442
    },
    "252794": {
      "name": "Adrián Bernabé",
      "cardName": "Adrián Bernabé",
      "originalVersionId": "1",
      "clubId": 50,
      "leagueId": 31,
      "countryId": 45,
      "versionId": "3001",
      "rating": 74,
      "preferredFoot": "Left",
      "weakFoot": 3,
      "skillMoves": 3,
      "preferredPosition": "CDM",
      "possiblePositions": [
        "CDM",
        "CM"
      ],
      "playStyles": [
        0,
        10,
        13,
        22
      ],
      "playStylesPlus": [],
      "rolesPlus": [
        16,
        21,
        49
      ],
      "rolesPlusPlus": [
        16,
        21,
        49
      ],
      "attributes": [
        77,
        70,
        75,
        79,
        69,
        63
      ],
      "hasDynamicImage": false,
      "price": 1100,
      "resourceId": 252794,
      "assetId": 252794
    },
    "255460": {
      "name": "Jacob Ondrejka",
      "cardName": "Ondrejka",
      "originalVersionId": "1",
      "clubId": 50,
      "leagueId": 31,
      "countryId": 46,
      "versionId": "3001",
      "rating": 73,
      "preferredFoot": "Right",
      "weakFoot": 4,
      "skillMoves": 4,
      "preferredPosition": "LM",
      "possiblePositions": [
        "LM",
        "LW"
      ],
      "playStyles": [
        0,
        12,
        21,
        8
      ],
      "playStylesPlus": [],
      "rolesPlus": [
        27,
        30,
        39
      ],
      "rolesPlusPlus": [
        27,
        30,
        39
      ],
      "attributes": [
        78,
        73,
        71,
        75,
        46,
        57
      ],
      "hasDynamicImage": false,
      "price": 550,
      "resourceId": 255460,
      "assetId": 255460
    },
    "255981": {
      "name": "Zion Suzuki",
      "cardName": "Suzuki",
      "originalVersionId": "1",
      "clubId": 50,
      "leagueId": 31,
      "countryId": 163,
      "versionId": "3001",
      "rating": 74,
      "preferredFoot": "Right",
      "weakFoot": 3,
      "skillMoves": 1,
      "preferredPosition": "GK",
      "possiblePositions": [
        "GK"
      ],
      "playStyles": [
        10,
        32
      ],
      "playStylesPlus": [],
      "rolesPlus": [
        45
      ],
      "rolesPlusPlus": [
        45
      ],
      "attributes": [
        73,
        72,
        71,
        76,
        56,
        73
      ],
      "hasDynamicImage": false,
      "price": 4000,
      "resourceId": 255981,
      "assetId": 255981
    },
    "257972": {
      "name": "Oliver Sørensen",
      "cardName": "Sørensen",
      "originalVersionId": "1",
      "clubId": 50,
      "leagueId": 31,
      "countryId": 13,
      "versionId": "3001",
      "rating": 73,
      "preferredFoot": "Left",
      "weakFoot": 3,
      "skillMoves": 3,
      "preferredPosition": "CM",
      "possiblePositions": [
        "CAM",
        "CM"
      ],
      "playStyles": [
        19
      ],
      "playStylesPlus": [],
      "rolesPlus": [
        22
      ],
      "rolesPlusPlus": [
        22
      ],
      "attributes": [
        73,
        68,
        69,
        71,
        68,
        80
      ],
      "hasDynamicImage": false,
      "price": 650,
      "resourceId": 257972,
      "assetId": 257972
    },
    "258708": {
      "name": "Botond Balogh",
      "cardName": "Balogh",
      "originalVersionId": "0",
      "clubId": 50,
      "leagueId": 31,
      "countryId": 23,
      "versionId": "2001",
      "rating": 70,
      "preferredFoot": "Right",
      "weakFoot": 3,
      "skillMoves": 2,
      "preferredPosition": "CB",
      "possiblePositions": [
        "CB"
      ],
      "playStyles": [],
      "playStylesPlus": [],
      "rolesPlus": [
        11,
        48
      ],
      "rolesPlusPlus": [
        11,
        48
      ],
      "attributes": [
        50,
        33,
        50,
        49,
        72,
        67
      ],
      "hasDynamicImage": false,
      "price": 0,
      "resourceId": 258708,
      "assetId": 258708
    },
    "258714": {
      "name": "Emanuele Valeri",
      "cardName": "Valeri",
      "originalVersionId": "0",
      "clubId": 50,
      "leagueId": 31,
      "countryId": 27,
      "versionId": "2002",
      "rating": 75,
      "preferredFoot": "Left",
      "weakFoot": 2,
      "skillMoves": 3,
      "preferredPosition": "LB",
      "possiblePositions": [
        "LB",
        "LM"
      ],
      "playStyles": [
        15,
        17,
        27
      ],
      "playStylesPlus": [],
      "rolesPlus": [
        9
      ],
      "rolesPlusPlus": [
        9
      ],
      "attributes": [
        74,
        70,
        73,
        74,
        71,
        66
      ],
      "hasDynamicImage": false,
      "price": 400,
      "resourceId": 258714,
      "assetId": 258714
    },
    "259150": {
      "name": "Abdoulaye Ndiaye",
      "cardName": "Ndiaye",
      "originalVersionId": "0",
      "clubId": 50,
      "leagueId": 31,
      "countryId": 136,
      "versionId": "2002",
      "rating": 75,
      "preferredFoot": "Left",
      "weakFoot": 2,
      "skillMoves": 2,
      "preferredPosition": "CB",
      "possiblePositions": [
        "CB"
      ],
      "playStyles": [
        14,
        18
      ],
      "playStylesPlus": [],
      "rolesPlus": [
        11,
        12,
        48
      ],
      "rolesPlusPlus": [
        11,
        12,
        48
      ],
      "attributes": [
        67,
        31,
        51,
        51,
        75,
        75
      ],
      "hasDynamicImage": false,
      "price": 350,
      "resourceId": 259150,
      "assetId": 259150
    },
    "261539": {
      "name": "Mandela Keita",
      "cardName": "Keita",
      "originalVersionId": "1",
      "clubId": 50,
      "leagueId": 31,
      "countryId": 7,
      "versionId": "3001",
      "rating": 73,
      "preferredFoot": "Right",
      "weakFoot": 3,
      "skillMoves": 3,
      "preferredPosition": "CDM",
      "possiblePositions": [
        "CB",
        "CDM",
        "CM"
      ],
      "playStyles": [],
      "playStylesPlus": [],
      "rolesPlus": [
        14,
        15,
        18
      ],
      "rolesPlusPlus": [
        14,
        15,
        18
      ],
      "attributes": [
        77,
        56,
        66,
        75,
        71,
        76
      ],
      "hasDynamicImage": false,
      "price": 850,
      "resourceId": 261539,
      "assetId": 261539
    },
    "263229": {
      "name": "Mateo Pellegrino",
      "cardName": "Pellegrino",
      "originalVersionId": "0",
      "clubId": 50,
      "leagueId": 31,
      "countryId": 52,
      "versionId": "2001",
      "rating": 67,
      "preferredFoot": "Left",
      "weakFoot": 4,
      "skillMoves": 2,
      "preferredPosition": "ST",
      "possiblePositions": [
        "ST"
      ],
      "playStyles": [
        29,
        4
      ],
      "playStylesPlus": [],
      "rolesPlus": [
        41
      ],
      "rolesPlusPlus": [
        41
      ],
      "attributes": [
        55,
        67,
        49,
        62,
        30,
        71
      ],
      "hasDynamicImage": false,
      "price": 500,
      "resourceId": 263229,
      "assetId": 263229
    },
    "264294": {
      "name": "Mathias Løvik",
      "cardName": "Løvik",
      "originalVersionId": "1",
      "clubId": 50,
      "leagueId": 31,
      "countryId": 36,
      "versionId": "3001",
      "rating": 65,
      "preferredFoot": "Left",
      "weakFoot": 4,
      "skillMoves": 2,
      "preferredPosition": "LB",
      "possiblePositions": [
        "LB",
        "LM"
      ],
      "playStyles": [],
      "playStylesPlus": [],
      "rolesPlus": [
        9,
        10,
        30
      ],
      "rolesPlusPlus": [
        9,
        10,
        30
      ],
      "attributes": [
        81,
        39,
        57,
        64,
        60,
        65
      ],
      "hasDynamicImage": false,
      "price": 950,
      "resourceId": 264294,
      "assetId": 264294
    },
    "268464": {
      "name": "Gabriel Charpentier",
      "cardName": "Charpentier",
      "originalVersionId": "0",
      "clubId": 50,
      "leagueId": 31,
      "countryId": 107,
      "versionId": "2001",
      "rating": 66,
      "preferredFoot": "Right",
      "weakFoot": 3,
      "skillMoves": 2,
      "preferredPosition": "ST",
      "possiblePositions": [
        "ST"
      ],
      "playStyles": [
        4
      ],
      "playStylesPlus": [],
      "rolesPlus": [
        41
      ],
      "rolesPlusPlus": [
        41
      ],
      "attributes": [
        51,
        67,
        48,
        66,
        27,
        64
      ],
      "hasDynamicImage": false,
      "price": 0,
      "resourceId": 268464,
      "assetId": 268464
    },
    "268913": {
      "name": "Alessandro Circati",
      "cardName": "Circati",
      "originalVersionId": "0",
      "clubId": 50,
      "leagueId": 31,
      "countryId": 195,
      "versionId": "2001",
      "rating": 71,
      "preferredFoot": "Right",
      "weakFoot": 3,
      "skillMoves": 2,
      "preferredPosition": "CB",
      "possiblePositions": [
        "CB"
      ],
      "playStyles": [
        19
      ],
      "playStylesPlus": [],
      "rolesPlus": [
        11,
        12
      ],
      "rolesPlusPlus": [
        11,
        12
      ],
      "attributes": [
        59,
        35,
        53,
        49,
        72,
        77
      ],
      "hasDynamicImage": false,
      "price": 650,
      "resourceId": 268913,
      "assetId": 268913
    },
    "268914": {
      "name": "Dario Sits",
      "cardName": "Sits",
      "originalVersionId": "0",
      "clubId": 50,
      "leagueId": 31,
      "countryId": 28,
      "versionId": "2000",
      "rating": 61,
      "preferredFoot": "Right",
      "weakFoot": 3,
      "skillMoves": 3,
      "preferredPosition": "ST",
      "possiblePositions": [
        "ST"
      ],
      "playStyles": [],
      "playStylesPlus": [],
      "rolesPlus": [
        41
      ],
      "rolesPlusPlus": [
        41
      ],
      "attributes": [
        53,
        62,
        48,
        56,
        28,
        63
      ],
      "hasDynamicImage": false,
      "price": 200,
      "resourceId": 268914,
      "assetId": 268914
    },
    "271385": {
      "name": "Edoardo Corvi",
      "cardName": "Corvi",
      "originalVersionId": "0",
      "clubId": 50,
      "leagueId": 31,
      "countryId": 27,
      "versionId": "2001",
      "rating": 65,
      "preferredFoot": "Right",
      "weakFoot": 1,
      "skillMoves": 1,
      "preferredPosition": "GK",
      "possiblePositions": [
        "GK"
      ],
      "playStyles": [],
      "playStylesPlus": [],
      "rolesPlus": [
        1
      ],
      "rolesPlusPlus": [
        1
      ],
      "attributes": [
        66,
        63,
        65,
        68,
        25,
        58
      ],
      "hasDynamicImage": false,
      "price": 850,
      "resourceId": 271385,
      "assetId": 271385
    },
    "273884": {
      "name": "Christian Ordoñez",
      "cardName": "Ordoñez",
      "originalVersionId": "1",
      "clubId": 50,
      "leagueId": 31,
      "countryId": 52,
      "versionId": "3001",
      "rating": 72,
      "preferredFoot": "Right",
      "weakFoot": 3,
      "skillMoves": 2,
      "preferredPosition": "CDM",
      "possiblePositions": [
        "CDM",
        "CM"
      ],
      "playStyles": [
        19
      ],
      "playStylesPlus": [],
      "rolesPlus": [
        14,
        17,
        18
      ],
      "rolesPlusPlus": [
        14,
        17,
        18
      ],
      "attributes": [
        83,
        45,
        64,
        70,
        66,
        81
      ],
      "hasDynamicImage": false,
      "price": 700,
      "resourceId": 273884,
      "assetId": 273884
    },
    "274442": {
      "name": "Antoine Joujou",
      "cardName": "Joujou",
      "originalVersionId": "1",
      "clubId": 50,
      "leagueId": 31,
      "countryId": 18,
      "versionId": "3001",
      "rating": 69,
      "preferredFoot": "Right",
      "weakFoot": 3,
      "skillMoves": 3,
      "preferredPosition": "LM",
      "possiblePositions": [
        "LM",
        "LW",
        "RM"
      ],
      "playStyles": [],
      "playStylesPlus": [],
      "rolesPlus": [
        23,
        27,
        29
      ],
      "rolesPlusPlus": [
        23,
        27,
        29
      ],
      "attributes": [
        70,
        65,
        63,
        71,
        22,
        53
      ],
      "hasDynamicImage": false,
      "price": 0,
      "resourceId": 274442,
      "assetId": 274442
    },
    "275401": {
      "name": "Matija Frigan",
      "cardName": "Frigan",
      "originalVersionId": "1",
      "clubId": 50,
      "leagueId": 31,
      "countryId": 10,
      "versionId": "3001",
      "rating": 73,
      "preferredFoot": "Left",
      "weakFoot": 4,
      "skillMoves": 2,
      "preferredPosition": "ST",
      "possiblePositions": [
        "ST"
      ],
      "playStyles": [
        4,
        6
      ],
      "playStylesPlus": [],
      "rolesPlus": [
        41
      ],
      "rolesPlusPlus": [
        41
      ],
      "attributes": [
        79,
        73,
        60,
        72,
        37,
        76
      ],
      "hasDynamicImage": false,
      "price": 750,
      "resourceId": 275401,
      "assetId": 275401
    },
    "276736": {
      "name": "Tjaš Begić",
      "cardName": "Begić",
      "originalVersionId": "1",
      "clubId": 50,
      "leagueId": 31,
      "countryId": 44,
      "versionId": "3001",
      "rating": 65,
      "preferredFoot": "Right",
      "weakFoot": 2,
      "skillMoves": 3,
      "preferredPosition": "CM",
      "possiblePositions": [
        "CAM",
        "CM"
      ],
      "playStyles": [],
      "playStylesPlus": [],
      "rolesPlus": [
        22
      ],
      "rolesPlusPlus": [
        22
      ],
      "attributes": [
        79,
        61,
        64,
        69,
        44,
        54
      ],
      "hasDynamicImage": false,
      "price": 6000,
      "resourceId": 276736,
      "assetId": 276736
    },
    "278280": {
      "name": "Filippo Rinaldi",
      "cardName": "Rinaldi",
      "originalVersionId": "0",
      "clubId": 50,
      "leagueId": 31,
      "countryId": 27,
      "versionId": "2000",
      "rating": 62,
      "preferredFoot": "Right",
      "weakFoot": 3,
      "skillMoves": 1,
      "preferredPosition": "GK",
      "possiblePositions": [
        "GK"
      ],
      "playStyles": [],
      "playStylesPlus": [],
      "rolesPlus": [
        1
      ],
      "rolesPlusPlus": [
        1
      ],
      "attributes": [
        61,
        62,
        62,
        65,
        22,
        56
      ],
      "hasDynamicImage": false,
      "price": 200,
      "resourceId": 278280,
      "assetId": 278280
    },
    "278287": {
      "name": "Anas Haj Mohamed",
      "cardName": "Haj Mohamed",
      "originalVersionId": "0",
      "clubId": 50,
      "leagueId": 31,
      "countryId": 145,
      "versionId": "2001",
      "rating": 65,
      "preferredFoot": "Right",
      "weakFoot": 3,
      "skillMoves": 3,
      "preferredPosition": "CAM",
      "possiblePositions": [
        "CAM",
        "CM"
      ],
      "playStyles": [],
      "playStylesPlus": [],
      "rolesPlus": [
        31
      ],
      "rolesPlusPlus": [
        31
      ],
      "attributes": [
        55,
        61,
        61,
        67,
        32,
        40
      ],
      "hasDynamicImage": false,
      "price": 0,
      "resourceId": 278287,
      "assetId": 278287
    },
    "278436": {
      "name": "Mariano Troilo",
      "cardName": "Troilo",
      "originalVersionId": "0",
      "clubId": 50,
      "leagueId": 31,
      "countryId": 52,
      "versionId": "2001",
      "rating": 66,
      "preferredFoot": "Right",
      "weakFoot": 3,
      "skillMoves": 2,
      "preferredPosition": "CB",
      "possiblePositions": [
        "CB"
      ],
      "playStyles": [],
      "playStylesPlus": [],
      "rolesPlus": [
        11,
        12
      ],
      "rolesPlusPlus": [
        11,
        12
      ],
      "attributes": [
        43,
        29,
        43,
        45,
        64,
        76
      ],
      "hasDynamicImage": false,
      "price": 600,
      "resourceId": 278436,
      "assetId": 278436
    },
    "278976": {
      "name": "Peter Amoran",
      "cardName": "Amoran",
      "originalVersionId": "0",
      "clubId": 50,
      "leagueId": 31,
      "countryId": 46,
      "versionId": "2000",
      "rating": 61,
      "preferredFoot": "Right",
      "weakFoot": 3,
      "skillMoves": 2,
      "preferredPosition": "CB",
      "possiblePositions": [
        "CB"
      ],
      "playStyles": [],
      "playStylesPlus": [],
      "rolesPlus": [
        11
      ],
      "rolesPlusPlus": [
        11
      ],
      "attributes": [
        60,
        28,
        45,
        46,
        61,
        63
      ],
      "hasDynamicImage": false,
      "price": 0,
      "resourceId": 278976,
      "assetId": 278976
    },
    "50407295": {
      "name": "Sascha Britschgi",
      "cardName": "Britschgi",
      "originalVersionId": "0",
      "clubId": 50,
      "leagueId": 31,
      "countryId": 47,
      "versionId": "2000",
      "rating": 52,
      "preferredFoot": "Right",
      "weakFoot": 2,
      "skillMoves": 2,
      "preferredPosition": "RB",
      "possiblePositions": [
        "LB",
        "RB",
        "RM"
      ],
      "playStyles": [],
      "playStylesPlus": [],
      "rolesPlus": [
        3
      ],
      "rolesPlusPlus": [
        3
      ],
      "attributes": [
        67,
        27,
        31,
        47,
        49,
        56
      ],
      "hasDynamicImage": false,
      "price": 200,
      "resourceId": 50407295,
      "assetId": 75647
    },
    "50569363": {
      "name": "Patrick Cutrone",
      "cardName": "Cutrone",
      "originalVersionId": "0",
      "clubId": 50,
      "leagueId": 31,
      "countryId": 27,
      "versionId": "2002",
      "rating": 75,
      "preferredFoot": "Right",
      "weakFoot": 3,
      "skillMoves": 3,
      "preferredPosition": "ST",
      "possiblePositions": [
        "ST"
      ],
      "playStyles": [],
      "playStylesPlus": [],
      "rolesPlus": [
        41
      ],
      "rolesPlusPlus": [
        41
      ],
      "attributes": [
        73,
        74,
        64,
        76,
        29,
        69
      ],
      "hasDynamicImage": false,
      "price": 400,
      "resourceId": 50569363,
      "assetId": 237715
    },
    "50600924": {
      "name": "Gaetano Oristanio",
      "cardName": "Oristanio",
      "originalVersionId": "1",
      "clubId": 50,
      "leagueId": 31,
      "countryId": 27,
      "versionId": "3001",
      "rating": 74,
      "preferredFoot": "Left",
      "weakFoot": 4,
      "skillMoves": 3,
      "preferredPosition": "CAM",
      "possiblePositions": [
        "CAM",
        "CM",
        "ST"
      ],
      "playStyles": [
        7
      ],
      "playStylesPlus": [],
      "rolesPlus": [
        31,
        33,
        42
      ],
      "rolesPlusPlus": [
        31,
        33,
        42
      ],
      "attributes": [
        85,
        72,
        69,
        77,
        51,
        64
      ],
      "hasDynamicImage": false,
      "price": 3000,
      "resourceId": 50600924,
      "assetId": 269276
    },
    "50604335": {
      "name": "Benjamin Cremaschi",
      "cardName": "Cremaschi",
      "originalVersionId": "0",
      "clubId": 50,
      "leagueId": 31,
      "countryId": 95,
      "versionId": "2001",
      "rating": 68,
      "preferredFoot": "Right",
      "weakFoot": 3,
      "skillMoves": 3,
      "preferredPosition": "CM",
      "possiblePositions": [
        "CAM",
        "CM",
        "RM"
      ],
      "playStyles": [],
      "playStylesPlus": [],
      "rolesPlus": [
        18
      ],
      "rolesPlusPlus": [
        18
      ],
      "attributes": [
        74,
        57,
        64,
        72,
        58,
        58
      ],
      "hasDynamicImage": false,
      "price": 1600,
      "resourceId": 50604335,
      "assetId": 272687
    }
  }
}